devtools_number_words/__init__.py
devtools_number_words-1.0.1.dist-info/METADATA
devtools_number_words-1.0.1.dist-info/WHEEL
devtools_number_words-1.0.1.dist-info/top_level.txt
devtools_number_words-1.0.1.dist-info/RECORD
