Metadata-Version: 2.1
Name: devtools-number-words
Version: 1.0.1
Summary: Number to words converter
Home-page: https://devtools.at/tools/number-to-words
Author: DevTools.at
Author-email: hello@devtools.at
Project-URL: Homepage, https://devtools.at/tools/number-to-words
Project-URL: Repository, https://github.com/devtools-at/number-to-words
Classifier: Development Status :: 4 - Beta
Classifier: Intended Audience :: Developers
Classifier: License :: OSI Approved :: MIT License
Classifier: Programming Language :: Python :: 3
Requires-Python: >=3.8
